minkipy/__init__.py
minkipy/commands.py
minkipy/constants.py
minkipy/defaults.py
minkipy/projects.py
minkipy/provides.py
minkipy/pyos_extensions.py
minkipy/pyshim.py
minkipy/queues.py
minkipy/settings.py
minkipy/tasks.py
minkipy/utils.py
minkipy/version.py
minkipy/workers.py
minkipy/cli/__init__.py
minkipy/cli/main.py
minkipy/cli/project.py
minkipy-0.2.22.dist-info/METADATA
minkipy-0.2.22.dist-info/WHEEL
minkipy-0.2.22.dist-info/entry_points.txt
minkipy-0.2.22.dist-info/top_level.txt
minkipy-0.2.22.dist-info/RECORD
